LICENSE
MANIFEST.in
README.md
requirements.txt
setup.cfg
setup.py
ckanext/__init__.py
ckanext/dataviewanalytics/__init__.py
ckanext/dataviewanalytics/db.py
ckanext/dataviewanalytics/plugin.py
ckanext/dataviewanalytics/controllers/__init__.py
ckanext/dataviewanalytics/controllers/ui_controller.py
ckanext/dataviewanalytics/templates/macros/form.html
ckanext/dataviewanalytics/templates/package/resource_read.html
ckanext/dataviewanalytics/templates/user/edit_user_form.html
ckanext/dataviewanalytics/templates/user/new_user_form.html
ckanext/dataviewanalytics/tests/__init__.py
ckanext/dataviewanalytics/tests/test_plugin.py
ckanext_dataviewanalytics.egg-info/PKG-INFO
ckanext_dataviewanalytics.egg-info/SOURCES.txt
ckanext_dataviewanalytics.egg-info/dependency_links.txt
ckanext_dataviewanalytics.egg-info/entry_points.txt
ckanext_dataviewanalytics.egg-info/namespace_packages.txt
ckanext_dataviewanalytics.egg-info/pbr.json
ckanext_dataviewanalytics.egg-info/top_level.txt