Metadata-Version: 1.1
Name: ckanext-dataviewanalytics
Version: 0.0.1
Summary: Provides analytics on data viewership
Home-page: https://github.com/daumie/ckanext-dataviewanalytics
Author: Ignatius Ukwuoma, Dominic Motuka
Author-email: dominic.motuka@gmail.com , ignatius.ukwuoma@andela.com
License: AGPL
Keywords: CKAN data viewership analytics
Platform: UNKNOWN
Classifier: Development Status :: 4 - Beta
Classifier: License :: OSI Approved :: GNU Affero General Public License v3 or later (AGPLv3+)
Classifier: Programming Language :: Python :: 2.7
